ehrt/__init__.py
ehrt-0.1.4.dist-info/METADATA
ehrt-0.1.4.dist-info/WHEEL
ehrt-0.1.4.dist-info/top_level.txt
ehrt-0.1.4.dist-info/RECORD
