Metadata-Version: 2.1
Name: ehrt
Version: 0.1.4
Summary: EHR Processing Toolkit
Author: Vidul Ayakulangara Panickan
Requires-Python: >=3.6
Requires-Dist: petehr
